README.rst
setup.py
djangocms_oscar/__init__.py
djangocms_oscar/admin.py
djangocms_oscar/cms_app.py
djangocms_oscar/cms_plugins.py
djangocms_oscar/models.py
djangocms_oscar/tests.py
djangocms_oscar/views.py
djangocms_oscar.egg-info/PKG-INFO
djangocms_oscar.egg-info/SOURCES.txt
djangocms_oscar.egg-info/dependency_links.txt
djangocms_oscar.egg-info/requires.txt
djangocms_oscar.egg-info/top_level.txt
djangocms_oscar/migrations/0001_initial.py
djangocms_oscar/migrations/__init__.py