Metadata-Version: 1.1
Name: djangocms-oscar
Version: 0.1
Summary: django CMS plugin for Oscar
Home-page: UNKNOWN
Author: Maik Hoepfel
Author-email: maik.hoepfel@tangentlabs.co.uk
License: BSD
Platform: linux
Classifier: Development Status :: 3 - Alpha
Classifier: Environment :: Web Environment
Classifier: Framework :: Django
Classifier: Intended Audience :: Developers
Classifier: License :: OSI Approved :: BSD License
Classifier: Operating System :: Unix
Classifier: Programming Language :: Python
Classifier: Programming Language :: Python :: 2
Classifier: Programming Language :: Python :: 2.7
Classifier: Topic :: Internet :: WWW/HTTP
